{
  "fs_idxs2graph_idxs": {
    "4": 1,
    "5": 2,
    "8": 3,
    "10": 4,
    "11": 5,
    "12": 6,
    "13": 7,
    "14": 8,
    "15": 9,
    "16": 10,
    "17": 11,
    "18": 12,
    "24": 13,
    "26": 14,
    "28": 15,
    "30": 16,
    "31": 17,
    "43": 18,
    "44": 19,
    "47": 20,
    "49": 21,
    "50": 22,
    "51": 23,
    "52": 24,
    "53": 25,
    "54": 26,
    "58": 27,
    "60": 28,
    "62": 29,
    "63": 30,
    "1001": 31,
    "1002": 32,
    "1003": 33,
    "1005": 34,
    "1006": 35,
    "1007": 36,
    "1008": 37,
    "1009": 38,
    "1010": 39,
    "1011": 40,
    "1012": 41,
    "1013": 42,
    "1014": 43,
    "1015": 44,
    "1016": 45,
    "1017": 46,
    "1018": 47,
    "1019": 48,
    "1020": 49,
    "1021": 50,
    "1022": 51,
    "1023": 52,
    "1024": 53,
    "1025": 54,
    "1026": 55,
    "1027": 56,
    "1028": 57,
    "1029": 58,
    "1030": 59,
    "1031": 60,
    "1032": 61,
    "1033": 62,
    "1034": 63,
    "1035": 64,
    "2001": 65,
    "2002": 66,
    "2003": 67,
    "2005": 68,
    "2006": 69,
    "2007": 70,
    "2008": 71,
    "2009": 72,
    "2010": 73,
    "2011": 74,
    "2012": 75,
    "2013": 76,
    "2014": 77,
    "2015": 78,
    "2016": 79,
    "2017": 80,
    "2018": 81,
    "2019": 82,
    "2020": 83,
    "2021": 84,
    "2022": 85,
    "2023": 86,
    "2024": 87,
    "2025": 88,
    "2026": 89,
    "2027": 90,
    "2028": 91,
    "2029": 92,
    "2030": 93,
    "2031": 94,
    "2032": 95,
    "2033": 96,
    "2034": 97,
    "2035": 98
  },
  "fs_names2graph_idxs" : {
    "Left-Lateral-Ventricle": 1,
    "Left-Inf-Lat-Vent": 2,
    "Left-Cerebellum-Cortex": 3,
    "Left-Thalamus-Proper": 4,
    "Left-Caudate": 5,
    "Left-Putamen": 6,
    "Left-Pallidum": 7,
    "3rd-Ventricle": 8,
    "4th-Ventricle": 9,
    "Brain-Stem": 10,
    "Left-Hippocampus": 11,
    "Left-Amygdala": 12,
    "CSF": 13,
    "Left-Accumbens-area": 14,
    "Left-VentralDC": 15,
    "Left-vessel": 16,
    "Left-choroid-plexus": 17,
    "Right-Lateral-Ventricle": 18,
    "Right-Inf-Lat-Vent": 19,
    "Right-Cerebellum-Cortex": 20,
    "Right-Thalamus-Proper": 21,
    "Right-Caudate": 22,
    "Right-Putamen": 23,
    "Right-Pallidum": 24,
    "Right-Hippocampus": 25,
    "Right-Amygdala": 26,
    "Right-Accumbens-area": 27,
    "Right-VentralDC": 28,
    "Right-vessel": 29,
    "Right-choroid-plexus": 30,
    "ctx-lh-bankssts": 31,
    "ctx-lh-caudalanteriorcingulate": 32,
    "ctx-lh-caudalmiddlefrontal": 33,
    "ctx-lh-cuneus": 34,
    "ctx-lh-entorhinal": 35,
    "ctx-lh-fusiform": 36,
    "ctx-lh-inferiorparietal": 37,
    "ctx-lh-inferiortemporal": 38,
    "ctx-lh-isthmuscingulate": 39,
    "ctx-lh-lateraloccipital": 40,
    "ctx-lh-lateralorbitofrontal": 41,
    "ctx-lh-lingual": 42,
    "ctx-lh-medialorbitofrontal": 43,
    "ctx-lh-middletemporal": 44,
    "ctx-lh-parahippocampal": 45,
    "ctx-lh-paracentral": 46,
    "ctx-lh-parsopercularis": 47,
    "ctx-lh-parsorbitalis": 48,
    "ctx-lh-parstriangularis": 49,
    "ctx-lh-pericalcarine": 50,
    "ctx-lh-postcentral": 51,
    "ctx-lh-posteriorcingulate": 52,
    "ctx-lh-precentral": 53,
    "ctx-lh-precuneus": 54,
    "ctx-lh-rostralanteriorcingulate": 55,
    "ctx-lh-rostralmiddlefrontal": 56,
    "ctx-lh-superiorfrontal": 57,
    "ctx-lh-superiorparietal": 58,
    "ctx-lh-superiortemporal": 59,
    "ctx-lh-supramarginal": 60,
    "ctx-lh-frontalpole": 61,
    "ctx-lh-temporalpole": 62,
    "ctx-lh-transversetemporal": 63,
    "ctx-lh-insula": 64,
    "ctx-rh-bankssts": 65,
    "ctx-rh-caudalanteriorcingulate": 66,
    "ctx-rh-caudalmiddlefrontal": 67,
    "ctx-rh-cuneus": 68,
    "ctx-rh-entorhinal": 69,
    "ctx-rh-fusiform": 70,
    "ctx-rh-inferiorparietal": 71,
    "ctx-rh-inferiortemporal": 72,
    "ctx-rh-isthmuscingulate": 73,
    "ctx-rh-lateraloccipital": 74,
    "ctx-rh-lateralorbitofrontal": 75,
    "ctx-rh-lingual": 76,
    "ctx-rh-medialorbitofrontal": 77,
    "ctx-rh-middletemporal": 78,
    "ctx-rh-parahippocampal": 79,
    "ctx-rh-paracentral": 80,
    "ctx-rh-parsopercularis": 81,
    "ctx-rh-parsorbitalis": 82,
    "ctx-rh-parstriangularis": 83,
    "ctx-rh-pericalcarine": 84,
    "ctx-rh-postcentral": 85,
    "ctx-rh-posteriorcingulate": 86,
    "ctx-rh-precentral": 87,
    "ctx-rh-precuneus": 88,
    "ctx-rh-rostralanteriorcingulate": 89,
    "ctx-rh-rostralmiddlefrontal": 90,
    "ctx-rh-superiorfrontal": 91,
    "ctx-rh-superiorparietal": 92,
    "ctx-rh-superiortemporal": 93,
    "ctx-rh-supramarginal": 94,
    "ctx-rh-frontalpole": 95,
    "ctx-rh-temporalpole": 96,
    "ctx-rh-transversetemporal": 97,
    "ctx-rh-insula": 98
  },
  "fs_idxs2fs_names":{
    "1": "Left-Cerebral-Exterior",
    "2": "Left-Cerebral-White-Matter",
    "3": "Left-Cerebral-Cortex",
    "4": "Left-Lateral-Ventricle",
    "5": "Left-Inf-Lat-Vent",
    "6": "Left-Cerebellum-Exterior",
    "7": "Left-Cerebellum-White-Matter",
    "8": "Left-Cerebellum-Cortex",
    "9": "Left-Thalamus",
    "10": "Left-Thalamus-Proper",
    "11": "Left-Caudate",
    "12": "Left-Putamen",
    "13": "Left-Pallidum",
    "14": "3rd-Ventricle",
    "15": "4th-Ventricle",
    "16": "Brain-Stem",
    "17": "Left-Hippocampus",
    "18": "Left-Amygdala",
    "19": "Left-Insula",
    "20": "Left-Operculum",
    "21": "Line-1",
    "22": "Line-2",
    "23": "Line-3",
    "24": "CSF",
    "25": "Left-Lesion",
    "26": "Left-Accumbens-area",
    "27": "Left-Substancia-Nigra",
    "28": "Left-VentralDC",
    "29": "Left-undetermined",
    "30": "Left-vessel",
    "31": "Left-choroid-plexus",
    "32": "Left-F3orb",
    "33": "Left-lOg",
    "34": "Left-aOg",
    "35": "Left-mOg",
    "36": "Left-pOg",
    "37": "Left-Stellate",
    "38": "Left-Porg",
    "39": "Left-Aorg",
    "40": "Right-Cerebral-Exterior",
    "41": "Right-Cerebral-White-Matter",
    "42": "Right-Cerebral-Cortex",
    "43": "Right-Lateral-Ventricle",
    "44": "Right-Inf-Lat-Vent",
    "45": "Right-Cerebellum-Exterior",
    "46": "Right-Cerebellum-White-Matter",
    "47": "Right-Cerebellum-Cortex",
    "48": "Right-Thalamus",
    "49": "Right-Thalamus-Proper",
    "50": "Right-Caudate",
    "51": "Right-Putamen",
    "52": "Right-Pallidum",
    "53": "Right-Hippocampus",
    "54": "Right-Amygdala",
    "55": "Right-Insula",
    "56": "Right-Operculum",
    "57": "Right-Lesion",
    "58": "Right-Accumbens-area",
    "59": "Right-Substancia-Nigra",
    "60": "Right-VentralDC",
    "61": "Right-undetermined",
    "62": "Right-vessel",
    "63": "Right-choroid-plexus",
    "64": "Right-F3orb",
    "65": "Right-lOg",
    "66": "Right-aOg",
    "67": "Right-mOg",
    "68": "Right-pOg",
    "69": "Right-Stellate",
    "70": "Right-Porg",
    "71": "Right-Aorg",
    "72": "5th-Ventricle",
    "73": "Left-Interior",
    "74": "Right-Interior",
    "77": "WM-hypointensities",
    "78": "Left-WM-hypointensities",
    "79": "Right-WM-hypointensities",
    "80": "non-WM-hypointensities",
    "81": "Left-non-WM-hypointensities",
    "82": "Right-non-WM-hypointensities",
    "83": "Left-F1",
    "84": "Right-F1",
    "85": "Optic-Chiasm",
    "192": "Corpus_Callosum",
    "86": "Left_future_WMSA",
    "87": "Right_future_WMSA",
    "88": "future_WMSA",
    "96": "Left-Amygdala-Anterior",
    "97": "Right-Amygdala-Anterior",
    "98": "Dura",
    "100": "Left-wm-intensity-abnormality",
    "101": "Left-caudate-intensity-abnormality",
    "102": "Left-putamen-intensity-abnormality",
    "103": "Left-accumbens-intensity-abnormality",
    "104": "Left-pallidum-intensity-abnormality",
    "105": "Left-amygdala-intensity-abnormality",
    "106": "Left-hippocampus-intensity-abnormality",
    "107": "Left-thalamus-intensity-abnormality",
    "108": "Left-VDC-intensity-abnormality",
    "109": "Right-wm-intensity-abnormality",
    "110": "Right-caudate-intensity-abnormality",
    "111": "Right-putamen-intensity-abnormality",
    "112": "Right-accumbens-intensity-abnormality",
    "113": "Right-pallidum-intensity-abnormality",
    "114": "Right-amygdala-intensity-abnormality",
    "115": "Right-hippocampus-intensity-abnormality",
    "116": "Right-thalamus-intensity-abnormality",
    "117": "Right-VDC-intensity-abnormality",
    "118": "Epidermis",
    "119": "Conn-Tissue",
    "120": "SC-Fat-Muscle",
    "121": "Cranium",
    "122": "CSF-SA",
    "123": "Muscle",
    "124": "Ear",
    "125": "Adipose",
    "126": "Spinal-Cord",
    "127": "Soft-Tissue",
    "128": "Nerve",
    "129": "Bone",
    "130": "Air",
    "131": "Orbital-Fat",
    "132": "Tongue",
    "133": "Nasal-Structures",
    "134": "Globe",
    "135": "Teeth",
    "136": "Left-Caudate-Putamen",
    "137": "Right-Caudate-Putamen",
    "138": "Left-Claustrum",
    "139": "Right-Claustrum",
    "140": "Cornea",
    "142": "Diploe",
    "143": "Vitreous-Humor",
    "144": "Lens",
    "145": "Aqueous-Humor",
    "146": "Outer-Table",
    "147": "Inner-Table",
    "148": "Periosteum",
    "149": "Endosteum",
    "150": "R-C-S",
    "151": "Iris",
    "152": "SC-Adipose-Muscle",
    "153": "SC-Tissue",
    "154": "Orbital-Adipose",
    "155": "Left-IntCapsule-Ant",
    "156": "Right-IntCapsule-Ant",
    "157": "Left-IntCapsule-Pos",
    "158": "Right-IntCapsule-Pos",
    "170": "brainstem",
    "171": "DCG",
    "172": "Vermis",
    "173": "Midbrain",
    "174": "Pons",
    "175": "Medulla",
    "177": "Vermis-White-Matter",
    "178": "SCP",
    "179": "Floculus",
    "180": "Left-Cortical-Dysplasia",
    "181": "Right-Cortical-Dysplasia",
    "182": "CblumNodulus",
    "193": "Left-hippocampal_fissure",
    "194": "Left-CADG-head",
    "195": "Left-subiculum",
    "196": "Left-fimbria",
    "197": "Right-hippocampal_fissure",
    "198": "Right-CADG-head",
    "199": "Right-subiculum",
    "200": "Right-fimbria",
    "201": "alveus",
    "202": "perforant_pathway",
    "203": "parasubiculum",
    "204": "presubiculum",
    "205": "subiculum",
    "206": "CA1",
    "207": "CA2",
    "208": "CA3",
    "209": "CA4",
    "210": "GC-DG",
    "211": "HATA",
    "212": "fimbria",
    "213": "lateral_ventricle",
    "214": "molecular_layer_HP",
    "215": "hippocampal_fissure",
    "216": "entorhinal_cortex",
    "217": "molecular_layer_subiculum",
    "218": "Amygdala",
    "219": "Cerebral_White_Matter",
    "220": "Cerebral_Cortex",
    "221": "Inf_Lat_Vent",
    "222": "Perirhinal",
    "223": "Cerebral_White_Matter_Edge",
    "224": "Background",
    "225": "Ectorhinal",
    "226": "HP_tail",
    "250": "Fornix",
    "251": "CC_Posterior",
    "252": "CC_Mid_Posterior",
    "253": "CC_Central",
    "254": "CC_Mid_Anterior",
    "255": "CC_Anterior",
    "1000": "ctx-lh-unknown",
    "1001": "ctx-lh-bankssts",
    "1002": "ctx-lh-caudalanteriorcingulate",
    "1003": "ctx-lh-caudalmiddlefrontal",
    "1004": "ctx-lh-corpuscallosum",
    "1005": "ctx-lh-cuneus",
    "1006": "ctx-lh-entorhinal",
    "1007": "ctx-lh-fusiform",
    "1008": "ctx-lh-inferiorparietal",
    "1009": "ctx-lh-inferiortemporal",
    "1010": "ctx-lh-isthmuscingulate",
    "1011": "ctx-lh-lateraloccipital",
    "1012": "ctx-lh-lateralorbitofrontal",
    "1013": "ctx-lh-lingual",
    "1014": "ctx-lh-medialorbitofrontal",
    "1015": "ctx-lh-middletemporal",
    "1016": "ctx-lh-parahippocampal",
    "1017": "ctx-lh-paracentral",
    "1018": "ctx-lh-parsopercularis",
    "1019": "ctx-lh-parsorbitalis",
    "1020": "ctx-lh-parstriangularis",
    "1021": "ctx-lh-pericalcarine",
    "1022": "ctx-lh-postcentral",
    "1023": "ctx-lh-posteriorcingulate",
    "1024": "ctx-lh-precentral",
    "1025": "ctx-lh-precuneus",
    "1026": "ctx-lh-rostralanteriorcingulate",
    "1027": "ctx-lh-rostralmiddlefrontal",
    "1028": "ctx-lh-superiorfrontal",
    "1029": "ctx-lh-superiorparietal",
    "1030": "ctx-lh-superiortemporal",
    "1031": "ctx-lh-supramarginal",
    "1032": "ctx-lh-frontalpole",
    "1033": "ctx-lh-temporalpole",
    "1034": "ctx-lh-transversetemporal",
    "1035": "ctx-lh-insula",
    "2000": "ctx-rh-unknown",
    "2001": "ctx-rh-bankssts",
    "2002": "ctx-rh-caudalanteriorcingulate",
    "2003": "ctx-rh-caudalmiddlefrontal",
    "2004": "ctx-rh-corpuscallosum",
    "2005": "ctx-rh-cuneus",
    "2006": "ctx-rh-entorhinal",
    "2007": "ctx-rh-fusiform",
    "2008": "ctx-rh-inferiorparietal",
    "2009": "ctx-rh-inferiortemporal",
    "2010": "ctx-rh-isthmuscingulate",
    "2011": "ctx-rh-lateraloccipital",
    "2012": "ctx-rh-lateralorbitofrontal",
    "2013": "ctx-rh-lingual",
    "2014": "ctx-rh-medialorbitofrontal",
    "2015": "ctx-rh-middletemporal",
    "2016": "ctx-rh-parahippocampal",
    "2017": "ctx-rh-paracentral",
    "2018": "ctx-rh-parsopercularis",
    "2019": "ctx-rh-parsorbitalis",
    "2020": "ctx-rh-parstriangularis",
    "2021": "ctx-rh-pericalcarine",
    "2022": "ctx-rh-postcentral",
    "2023": "ctx-rh-posteriorcingulate",
    "2024": "ctx-rh-precentral",
    "2025": "ctx-rh-precuneus",
    "2026": "ctx-rh-rostralanteriorcingulate",
    "2027": "ctx-rh-rostralmiddlefrontal",
    "2028": "ctx-rh-superiorfrontal",
    "2029": "ctx-rh-superiorparietal",
    "2030": "ctx-rh-superiortemporal",
    "2031": "ctx-rh-supramarginal",
    "2032": "ctx-rh-frontalpole",
    "2033": "ctx-rh-temporalpole",
    "2034": "ctx-rh-transversetemporal",
    "2035": "ctx-rh-insula"
  }
}